odoo/addons/stock_move_line_open_lot/README.rst
odoo/addons/stock_move_line_open_lot/__init__.py
odoo/addons/stock_move_line_open_lot/__manifest__.py
odoo/addons/stock_move_line_open_lot/i18n/es.po
odoo/addons/stock_move_line_open_lot/models/__init__.py
odoo/addons/stock_move_line_open_lot/models/stock_move_line.py
odoo/addons/stock_move_line_open_lot/models/stock_picking_type.py
odoo/addons/stock_move_line_open_lot/readme/CONTRIBUTORS.md
odoo/addons/stock_move_line_open_lot/readme/DESCRIPTION.md
odoo/addons/stock_move_line_open_lot/readme/USAGE.md
odoo/addons/stock_move_line_open_lot/static/description/icon.png
odoo/addons/stock_move_line_open_lot/static/description/index.html
odoo/addons/stock_move_line_open_lot/tests/__init__.py
odoo/addons/stock_move_line_open_lot/tests/test_stock_move_line_open_lot.py
odoo/addons/stock_move_line_open_lot/views/stock_move_views.xml
odoo/addons/stock_move_line_open_lot/views/stock_picking_type_views.xml
odoo_addon_stock_move_line_open_lot-17.0.1.0.0.1.dist-info/METADATA
odoo_addon_stock_move_line_open_lot-17.0.1.0.0.1.dist-info/WHEEL
odoo_addon_stock_move_line_open_lot-17.0.1.0.0.1.dist-info/top_level.txt
odoo_addon_stock_move_line_open_lot-17.0.1.0.0.1.dist-info/RECORD
